{
  "careeradvice": 5,
  "resumes": 5,
  "job-search-sites": 1,
  "job-hunting": 1,
  "job-applications": 2,
  "jobsearch": 8,
  "productivity": 1,
  "emailtips": 1,
  "emailhacks": 1,
  "organization": 1,
  "job-search": 5,
  "motivation": 1,
  "mental-health": 1,
  "it-jobs": 1,
  "burnout": 1,
  "resume": 1,
  "tech-jobs": 2,
  "it-market-trends": 1,
  "upskilling": 1,
  "tech-interviews": 1,
  "online-interview-tips": 1,
  "career-advice": 2,
  "resume-tips": 1,
  "portfolios": 1,
  "techskills": 2,
  "learning": 1,
  "humor": 1,
  "interviewtips": 2,
  "email": 1,
  "tech": 1,
  "techinterviews": 1
}
